package_teste_pacotes/__init__.py
package_teste_pacotes/file1_name.py
package_teste_pacotes/file2_name.py
package_teste_pacotes-0.0.1.dist-info/METADATA
package_teste_pacotes-0.0.1.dist-info/WHEEL
package_teste_pacotes-0.0.1.dist-info/top_level.txt
package_teste_pacotes-0.0.1.dist-info/RECORD
