Metadata-Version: 2.4
Name: package_teste_pacotes
Version: 0.0.1
Summary: Teste de Criação de Pacotes
Author: Fábio Alves
Author-email: fabio.dp.alves@gmail.com
Requires-Python: >=3.8
Dynamic: author
Dynamic: author-email
Dynamic: description
Dynamic: description-content-type
Dynamic: requires-python
Dynamic: summary
